Mergeexcel/__init__.py
Mergeexcel/merge.py
Mergeexcel/myMath.py
pyrdt/__init__.py
pyrdt/atom.py
pyrdt/combo.py
pyrdt/math.py
pyrdt/stat.py
pywfz/__init__.py
pywfz/myMath.py
pywfz/sql.py
pywfz/util.py
Mergeexcel-1.0.0.dist-info/LICENSE
Mergeexcel-1.0.0.dist-info/METADATA
Mergeexcel-1.0.0.dist-info/WHEEL
Mergeexcel-1.0.0.dist-info/top_level.txt
Mergeexcel-1.0.0.dist-info/RECORD
